<?xml version="1.0" encoding="utf-8" ?>
<Patch>
<Operation Class="PatchOperationSequence">
  <success>Always</success>
  <operations>
    <li Class="PatchOperationTest">
      <xpath>Defs/ResearchTabDef[defName="CE_Turrets"]</xpath>
    </li>
    <li Class="PatchOperationAdd">
        <success>Always</success>
        <xpath>Defs/ScenarioDef[defName="EldarScenarioTest"]/parts</xpath>
        <value>
			<li Class="ScenPart_StartingThing_Defined">
				<def>StartingThing_Defined</def>
				<thingDef>Ammo_OGShuriken</thingDef>
				<count>100</count>
			</li>
        </value>
    </li>
  </operations>
</Operation>

</Patch>
