<?xml version="1.0" encoding="utf-8" ?>
<Defs>

  <StyleCategoryDef>
    <defName>OG_Aeldari_Asuryani</defName>
    <label>asuryani</label>
    <iconPath>Icons/Eldar/Icon_Eldar_Craftworld</iconPath>
    <soundOngoingRitual>RitualSustainer_Morbid</soundOngoingRitual>
    <ritualVisualEffectDef>Morbid</ritualVisualEffectDef>
    <thingDefStyles>
      <li>
        <thingDef>SculptureSmall</thingDef>
        <styleDef>Morbid_SculptureSmall</styleDef>
      </li>
      <li>
        <thingDef>SculptureLarge</thingDef>
        <styleDef>Morbid_SculptureLarge</styleDef>
      </li>
      <li>
        <thingDef>SculptureGrand</thingDef>
        <styleDef>Morbid_SculptureGrand</styleDef>
      </li>
      <li>
        <thingDef>Altar_Small</thingDef>
        <styleDef>Morbid_AltarSmall</styleDef>
      </li>
      <li>
        <thingDef>Altar_Medium</thingDef>
        <styleDef>Morbid_AltarMedium</styleDef>
      </li>
      <li>
        <thingDef>Altar_Large</thingDef>
        <styleDef>Morbid_AltarLarge</styleDef>
      </li>
      <li>
        <thingDef>Altar_Grand</thingDef>
        <styleDef>Morbid_AltarGrand</styleDef>
      </li>
      <li>
        <thingDef>Stool</thingDef>
        <styleDef>Morbid_Stool</styleDef>
      </li>
      <li>
        <thingDef>Table1x2c</thingDef>
        <styleDef>Morbid_Table1x2c</styleDef>
      </li>
      <li>
        <thingDef>Table2x2c</thingDef>
        <styleDef>Morbid_Table2x2c</styleDef>
      </li>
      <li>
        <thingDef>Table2x4c</thingDef>
        <styleDef>Morbid_Table2x4c</styleDef>
      </li>
      <li>
        <thingDef>Table3x3c</thingDef>
        <styleDef>Morbid_Table3x3c</styleDef>
      </li>
      <li>
        <thingDef>StandingLamp</thingDef>
        <styleDef>Morbid_StandingLamp</styleDef>
      </li>
      <li>
        <thingDef>StandingLamp_Red</thingDef>
        <styleDef>Morbid_StandingLamp_Red</styleDef>
      </li>
      <li>
        <thingDef>StandingLamp_Green</thingDef>
        <styleDef>Morbid_StandingLamp_Green</styleDef>
      </li>
      <li>
        <thingDef>StandingLamp_Blue</thingDef>
        <styleDef>Morbid_StandingLamp_Blue</styleDef>
      </li>
      <li>
        <thingDef>Darklamp</thingDef>
        <styleDef>Morbid_DarklampStanding</styleDef>
      </li>
      <li>
        <thingDef>TorchLamp</thingDef>
        <styleDef>Morbid_TorchLamp</styleDef>
      </li>
      <li>
        <thingDef>Column</thingDef>
        <styleDef>Morbid_Column</styleDef>
      </li>
      <li>
        <thingDef>Apparel_ArmorHelmetRecon</thingDef>
        <styleDef>Morbid_ReconHelmet</styleDef>
      </li>
      <li>
        <thingDef>Apparel_PowerArmorHelmet</thingDef>
        <styleDef>Morbid_MarineHelmet</styleDef>
      </li>
      <li MayRequire="Ludeon.RimWorld.Royalty">
        <thingDef>Apparel_ArmorHelmetCataphract</thingDef>
        <styleDef>Morbid_CataphractHelmet</styleDef>
      </li>
      <li>
        <thingDef>Ideogram</thingDef>
        <styleDef>Morbid_IdeogramA</styleDef>
      </li>
      <li>
        <thingDef>Ideogram</thingDef>
        <styleDef>Morbid_IdeogramB</styleDef>
      </li>
    </thingDefStyles>
    <addDesignators>
      <li>MorbidSlab_Medium</li>
      <li>MorbidSlab_Broad</li>
    </addDesignators>
    <addDesignatorGroups>
      <li>Floor_Morbid_Stone</li>
      <li>Floor_Morbid_Carpet</li>
    </addDesignatorGroups>
  </StyleCategoryDef>

  <StyleCategoryDef>
    <defName>OG_Aeldari_Exodite</defName>
    <label>totemic</label>
    <iconPath>Icons/Eldar/Icon_Eldar_Exodite</iconPath>
    <soundOngoingRitual>RitualSustainer_Totemic</soundOngoingRitual>
    <ritualVisualEffectDef>Totemic</ritualVisualEffectDef>
    <thingDefStyles>
      <li>
        <thingDef>SculptureSmall</thingDef>
        <styleDef>Totemic_SculptureSmall</styleDef>
      </li>
      <li>
        <thingDef>SculptureLarge</thingDef>
        <styleDef>Totemic_SculptureLarge</styleDef>
      </li>
      <li>
        <thingDef>SculptureGrand</thingDef>
        <styleDef>Totemic_SculptureGrand</styleDef>
      </li>
      <li>
        <thingDef>Altar_Small</thingDef>
        <styleDef>Totemic_AltarSmall</styleDef>
      </li>
      <li>
        <thingDef>Altar_Medium</thingDef>
        <styleDef>Totemic_AltarMedium</styleDef>
      </li>
      <li>
        <thingDef>Altar_Large</thingDef>
        <styleDef>Totemic_AltarLarge</styleDef>
      </li>
      <li>
        <thingDef>Altar_Grand</thingDef>
        <styleDef>Totemic_AltarGrand</styleDef>
      </li>
      <li>
        <thingDef>Stool</thingDef>
        <styleDef>Totemic_Stool</styleDef>
      </li>
      <li>
        <thingDef>DiningChair</thingDef>
        <styleDef>Totemic_DiningChair</styleDef>
      </li>
      <li>
        <thingDef>Table1x2c</thingDef>
        <styleDef>Totemic_Table1x2c</styleDef>
      </li>
      <li>
        <thingDef>Table2x2c</thingDef>
        <styleDef>Totemic_Table2x2c</styleDef>
      </li>
      <li>
        <thingDef>Table2x4c</thingDef>
        <styleDef>Totemic_Table2x4c</styleDef>
      </li>
      <li>
        <thingDef>Table3x3c</thingDef>
        <styleDef>Totemic_Table3x3c</styleDef>
      </li>
      <li>
        <thingDef>StandingLamp</thingDef>
        <styleDef>Totemic_StandingLamp</styleDef>
      </li>
      <li>
        <thingDef>StandingLamp_Red</thingDef>
        <styleDef>Totemic_StandingLamp_Red</styleDef>
      </li>
      <li>
        <thingDef>StandingLamp_Green</thingDef>
        <styleDef>Totemic_StandingLamp_Green</styleDef>
      </li>
      <li>
        <thingDef>StandingLamp_Blue</thingDef>
        <styleDef>Totemic_StandingLamp_Blue</styleDef>
      </li>
      <li>
        <thingDef>Darklamp</thingDef>
        <styleDef>Totemic_DarklampStanding</styleDef>
      </li>
      <li>
        <thingDef>TorchLamp</thingDef>
        <styleDef>Totemic_TorchLamp</styleDef>
      </li>
      <li>
        <thingDef>Column</thingDef>
        <styleDef>Totemic_Column</styleDef>
      </li>
      <li>
        <thingDef>Apparel_ArmorHelmetRecon</thingDef>
        <styleDef>Totemic_ReconHelmet</styleDef>
      </li>
      <li>
        <thingDef>Apparel_PowerArmorHelmet</thingDef>
        <styleDef>Totemic_MarineHelmet</styleDef>
      </li>
      <li MayRequire="Ludeon.RimWorld.Royalty">
        <thingDef>Apparel_ArmorHelmetCataphract</thingDef>
        <styleDef>Totemic_CataphractHelmet</styleDef>
      </li>
      <li>
        <thingDef>Ideogram</thingDef>
        <styleDef>Totemic_IdeogramA</styleDef>
      </li>
      <li>
        <thingDef>Ideogram</thingDef>
        <styleDef>Totemic_IdeogramB</styleDef>
      </li>
    </thingDefStyles>
    <addDesignators>
      <li>TotemicSlab_Medium</li>
      <li>TotemicSlab_Broad</li>
      <li>Boards_Totemic</li>
    </addDesignators>
    <addDesignatorGroups>
      <li>Floor_Totemic_Tile</li>
    </addDesignatorGroups>
  </StyleCategoryDef>

  <StyleCategoryDef>
    <defName>OG_Aeldari_Drukhari</defName>
    <label>drukhari</label>
    <iconPath>Icons/DarkEldar/Icon_DarkEldar</iconPath>
    <soundOngoingRitual>RitualSustainer_Spikecore</soundOngoingRitual>
    <ritualVisualEffectDef>Spikecore</ritualVisualEffectDef>
    <thingDefStyles>
      <li>
        <thingDef>Table1x2c</thingDef>
        <styleDef>Spikecore_Table1x2c</styleDef>
      </li>
      <li>
        <thingDef>Table2x2c</thingDef>
        <styleDef>Spikecore_Table2x2c</styleDef>
      </li>
      <li>
        <thingDef>Table2x4c</thingDef>
        <styleDef>Spikecore_Table2x4c</styleDef>
      </li>
      <li>
        <thingDef>Table3x3c</thingDef>
        <styleDef>Spikecore_Table3x3c</styleDef>
      </li>
      <li>
        <thingDef>StandingLamp</thingDef>
        <styleDef>Spikecore_StandingLamp</styleDef>
      </li>
      <li>
        <thingDef>StandingLamp_Red</thingDef>
        <styleDef>Spikecore_StandingLamp_Red</styleDef>
      </li>
      <li>
        <thingDef>StandingLamp_Green</thingDef>
        <styleDef>Spikecore_StandingLamp_Green</styleDef>
      </li>
      <li>
        <thingDef>StandingLamp_Blue</thingDef>
        <styleDef>Spikecore_StandingLamp_Blue</styleDef>
      </li>
      <li>
        <thingDef>Darklamp</thingDef>
        <styleDef>Spikecore_DarklampStanding</styleDef>
      </li>
      <li>
        <thingDef>TorchLamp</thingDef>
        <styleDef>Spikecore_TorchLamp</styleDef>
      </li>
      <li>
        <thingDef>Column</thingDef>
        <styleDef>Spikecore_Column</styleDef>
      </li>
      <li>
        <thingDef>Apparel_SimpleHelmet</thingDef>
        <styleDef>Spikecore_SimpleHelmet</styleDef>
      </li>
      <li>
        <thingDef>Apparel_AdvancedHelmet</thingDef>
        <styleDef>Spikecore_AdvancedHelmet</styleDef>
      </li>
      <li>
        <thingDef>Apparel_FlakJacket</thingDef>
        <styleDef>Spikecore_FlakJacket</styleDef>
      </li>
      <li>
        <thingDef>Apparel_Duster</thingDef>
        <styleDef>Spikecore_Duster</styleDef>
      </li>
      <li>
        <thingDef>Apparel_Jacket</thingDef>
        <styleDef>Spikecore_Jacket</styleDef>
      </li>
      <li>
        <thingDef>Apparel_Parka</thingDef>
        <styleDef>Spikecore_Parka</styleDef>
      </li>
    </thingDefStyles>
    <addDesignators>
      <li>SpikecoreFloorStar_Medium</li>
      <li>SpikecoreFloorStar_Broad</li>
      <li>Plates_Spikecore</li>
    </addDesignators>
    <addDesignatorGroups>
      <li>Floor_Spikecore_Tile</li>
    </addDesignatorGroups>
  </StyleCategoryDef>

</Defs>