<?xml version="1.0" encoding="utf-8" ?>
<Defs>
    <!-- ========================= Eldar ========================== -->
    <!-- ========================= Eldar - Clothes Base - Apparel Base ========================== -->
	<ThingDef Name="OGEApparelBase" ParentName="OG_Apparel_Base" Abstract="True">
		<apparel>
			<tags>
				<li>EldarApparel</li>
			</tags>
		</apparel>
		<thingCategories>
			<li>OGESub</li>
		</thingCategories>
	</ThingDef>
	
    <!-- ========================= Eldar - Clothes Base - Apparel Makable Base ========================== -->
	<ThingDef Name="OGEApparelMakeableBase" ParentName="OGEApparelBase" Abstract="True">
		<recipeMaker>
			<workSpeedStat>GeneralLaborSpeed</workSpeedStat>
			<workSkill>Crafting</workSkill>
			<effectWorking>Tailor</effectWorking>
			<soundWorking>Recipe_Tailor</soundWorking>
			<recipeUsers>
				<li>ElectricTailoringBench</li>
				<li>HandTailoringBench</li>
			</recipeUsers>
			<unfinishedThingDef>UnfinishedApparel</unfinishedThingDef>
			<researchPrerequisites>
				<li>OG_Eldar_Tech_Base_T1</li>
			</researchPrerequisites>
		</recipeMaker>
	</ThingDef>
		
    <!-- ========================= Eldar - Clothes - Apparel Makable ========================== -->
	<ThingDef Name="OGEApparelMakeable" ParentName="OGEApparelMakeableBase" Abstract="True">
		<apparel>
			<tags>
				<li>EldarClothing</li>
			</tags>
		</apparel>
		<thingCategories>
			<li>OGEApparel</li>
		</thingCategories>
	</ThingDef>
	
	<!-- ========================= Eldar - Headgear - Hat Makable ========================== -->
	<ThingDef Name="OGEHatMakeable" ParentName="OGEApparelMakeableBase" Abstract="True">
		<apparel>
			<tags>
				<li>EldarHat</li>
			</tags>
		</apparel>
		<thingCategories>
			<li>OGEHeadgear</li>
		</thingCategories>
    <statBases>
      <Mass>0.15</Mass>
    </statBases>
	</ThingDef>
	
    <!-- ========================= Eldar - Clothes Base - Apparel Base ========================== -->
	<ThingDef Name="OGEArmorBase" ParentName="OG_Apparel_Base" Abstract="True">
		<apparel>
			<tags>
				<li>EldarApparel</li>
			</tags>
		</apparel>
		<thingCategories>
			<li>OGESub</li>
		</thingCategories>
	</ThingDef>

    <!-- ========================= Eldar - Apparel Armor Makable Base ========================== -->
	<ThingDef Name="OGEArmorMakeableBase" ParentName="OGEArmorBase" Abstract="True">
		<recipeMaker>
			<workSpeedStat>GeneralLaborSpeed</workSpeedStat>
			<workSkill>Crafting</workSkill>
			<effectWorking>Smith</effectWorking>
			<soundWorking>Recipe_Machining</soundWorking>
			<recipeUsers>
				<li>OGE_TableMachining</li>
			</recipeUsers>
			<unfinishedThingDef>UnfinishedTechArmor</unfinishedThingDef>
			<researchPrerequisites>
				<li>OG_Eldar_Tech_Base_T1</li>
			</researchPrerequisites>
		</recipeMaker>
	</ThingDef>
	
    <!-- ========================= Eldar - Apparel Armor Makable Base ========================== -->
	<ThingDef Name="OGEArmorMakeable" ParentName="OGEArmorMakeableBase" Abstract="True">
				<apparel>
			<tags>
				<li>OG_Aeldari_Tech_Apparel_Armour_T1</li>
			</tags>
		</apparel>
		<thingCategories>
			<li>OGEArmour</li>
		</thingCategories>
	</ThingDef>	
		
	<!-- ========================= Eldar - Headgear Base - Helmet Makable Base ========================== -->
	<ThingDef Name="OGEHelmetMakeable" ParentName="OGEArmorMakeableBase" Abstract="True">
		<apparel>
			<tags>
				<li>EldarHelmet</li>
			</tags>
		</apparel>
		<thingCategories>
			<li>OGEHeadgear</li>
		</thingCategories>
    <statBases>
      <Mass>0.35</Mass>
    </statBases>
	</ThingDef>
			
	<!-- ========================= Eldar - Apparel Wargear Base ========================== -->
	<ThingDef Name="OGEWargearBase" ParentName="OG_Apparel_Base" Abstract="True">
		<apparel>
			<tags>
				<li>EldarWargear</li>
			</tags>
		</apparel>
		<thingCategories>
			<li>OGEWargear</li>
		</thingCategories>
	</ThingDef>	
	
	<!-- ========================= Eldar - Apparel Wargear Makable Base ========================== -->
	<ThingDef Name="OGEWargearMakeable" ParentName="OGEWargearBase" Abstract="True">
		<recipeMaker>
			<workSpeedStat>GeneralLaborSpeed</workSpeedStat>
			<workSkill>Crafting</workSkill>
			<effectWorking>Smith</effectWorking>
			<soundWorking>Recipe_Machining</soundWorking>
			<recipeUsers>
				<li>OGE_TableMachining</li>
			</recipeUsers>
			<unfinishedThingDef>UnfinishedTechArmor</unfinishedThingDef>
			<researchPrerequisites>
				<li>OG_Eldar_Tech_Base_T1</li>
			</researchPrerequisites>
		</recipeMaker>
	</ThingDef>	
</Defs>